yarok/__init__.py
yarok/__main__.py
yarok/cli/__init__.py
yarok/cli/generate.py
yarok/comm/__init__.py
yarok/comm/components/__init__.py
yarok/comm/components/anet_a30/__init__.py
yarok/comm/components/anet_a30/anet_a30.py
yarok/comm/components/anet_a30/anet_a30.xml
yarok/comm/components/anet_a30/anet_at30.py
yarok/comm/components/anet_a30/meshes/CR-10_platform2.stl
yarok/comm/components/anet_a30/meshes/bed.stl
yarok/comm/components/anet_a30/meshes/bed2.stl
yarok/comm/components/anet_a30/meshes/bottom_frame.stl
yarok/comm/components/anet_a30/meshes/external_frame.stl
yarok/comm/components/anet_a30/meshes/side1_frame.stl
yarok/comm/components/anet_a30/meshes/side2_frame.stl
yarok/comm/components/anet_a30/meshes/x_axis.stl
yarok/comm/components/cam/__init__.py
yarok/comm/components/cam/cam.py
yarok/comm/components/digit/__init__.py
yarok/comm/components/digit/digit.py
yarok/comm/components/digit/digit.xml
yarok/comm/components/digit/env_test.py
yarok/comm/components/digit/assets/gel/background.png
yarok/comm/components/digit/assets/gel/background_d.png
yarok/comm/components/digit/assets/gel/digit_bg.png
yarok/comm/components/digit/assets/gel/digit_env.xml
yarok/comm/components/digit/assets/gel/digit_sensor.xml
yarok/comm/components/digit/assets/gel/shared.xml
yarok/comm/components/digit/utils/__init__.py
yarok/comm/components/digit/utils/phong_render.py
yarok/comm/components/gelsight/__init__.py
yarok/comm/components/gelsight/background_gelsight2014.png
yarok/comm/components/gelsight/gelsight2014.py
yarok/comm/components/gelsight/meshes/back_cover.stl
yarok/comm/components/gelsight/meshes/gelsight2014_back.stl
yarok/comm/components/gelsight/meshes/gelsight2014_front.stl
yarok/comm/components/gelsight/meshes/gelsight2014_smartlab.stl
yarok/comm/components/gelsight/meshes/glass.stl
yarok/comm/components/gelsight/meshes/mountable_gelsight.stl
yarok/comm/components/gelsight/model/__init__.py
yarok/comm/components/gelsight/model/simulation_model.py
yarok-0.0.40.dist-info/METADATA
yarok-0.0.40.dist-info/WHEEL
yarok-0.0.40.dist-info/entry_points.txt
yarok-0.0.40.dist-info/top_level.txt
yarok-0.0.40.dist-info/RECORD
