Metadata-Version: 2.1
Name: yarok
Version: 0.0.40
Summary: YAROK - Yet another robot framework
Home-page: https://github.com/danfergo/yarok
Author: danfergo
Author-email: danfergo@gmail.com
Keywords: yarok,robot,framework,mujoco
Requires-Dist: mujoco
Requires-Dist: mujoco-python-viewer
Requires-Dist: pyyaml
